checksentry/__init__.py
checksentry/config.py
checksentry/main.py
checksentry/sentry.py
checksentry-0.1.2.dist-info/METADATA
checksentry-0.1.2.dist-info/WHEEL
checksentry-0.1.2.dist-info/entry_points.txt
checksentry-0.1.2.dist-info/RECORD
